jt_calc/__init__.py
jt_calc-0.0.2.dist-info/LICENCE
jt_calc-0.0.2.dist-info/METADATA
jt_calc-0.0.2.dist-info/WHEEL
jt_calc-0.0.2.dist-info/top_level.txt
jt_calc-0.0.2.dist-info/RECORD
