Metadata-Version: 2.1
Name: jt-calc
Version: 0.0.2
Summary: Custom calculator in Python 3.7
Home-page: https://bitbucket.org/tilsedtowers/jt_calc/src
Author: Joe Tilsed
Author-email: Joe@Tilsed.com
License: UNKNOWN
Platform: UNKNOWN
Classifier: Programming Language :: Python :: 3.7
Classifier: License :: OSI Approved :: MIT License
Classifier: Operating System :: OS Independent
